geodata/__init__.py
geodata/core/__init__.py
geodata/core/base.py
geodata/core/geolevel.py
geodata/core/quality.py
ibge_geodata-1.0.0.dist-info/LICENSE.md
ibge_geodata-1.0.0.dist-info/METADATA
ibge_geodata-1.0.0.dist-info/WHEEL
ibge_geodata-1.0.0.dist-info/RECORD
